openapi_ai/__init__.py
openapi_ai/component.py
openapi_ai/endpoint.py
openapi_ai/generator.py
openapi_ai/loader.py
openapi_ai/openapi_tools.py
openapi_ai/schema.py
openapi_ai/type.py
openapi_ai-0.4.0.dist-info/METADATA
openapi_ai-0.4.0.dist-info/WHEEL
openapi_ai-0.4.0.dist-info/top_level.txt
openapi_ai-0.4.0.dist-info/RECORD
