Metadata-Version: 2.4
Name: openapi-ai
Version: 0.4.0
Summary: Python library to convert OpenAPI endpoints into callable tools for LLM AI agents.
Author-email: Aria Dhanang <ariadng@gmail.com>
License: MIT
Project-URL: Homepage, https://github.com/ariadng/openapi-agent-tools
Keywords: openapi,llm,ai,agent
Classifier: Programming Language :: Python :: 3
Classifier: License :: OSI Approved :: MIT License
Classifier: Operating System :: OS Independent
Requires-Python: >=3.10
Requires-Dist: requests>=2.32.3
Requires-Dist: pydantic>=2.11.4
Requires-Dist: openai-agents>=0.0.14
